{"E07000163":{"area_name":"Craven","value":80},"E07000164":{"area_name":"Hambleton","value":82.9},"E07000165":{"area_name":"Harrogate","value":79.9},"E07000166":{"area_name":"Richmondshire","value":65.3},"E07000167":{"area_name":"Ryedale","value":84.3},"E07000168":{"area_name":"Scarborough","value":72.2},"E07000169":{"area_name":"Selby","value":84.2},"E08000016":{"area_name":"Barnsley","value":71.8},"E08000017":{"area_name":"Doncaster","value":72.4},"E08000018":{"area_name":"Rotherham ","value":72.4},"E08000019":{"area_name":"Sheffield","value":72.4},"E08000032":{"area_name":"Bradford ","value":67.6},"E08000033":{"area_name":"Calderdale","value":73.6},"E08000034":{"area_name":"Kirklees ","value":72.7},"E08000035":{"area_name":"Leeds ","value":77.5},"E08000036":{"area_name":"Wakefield","value":73.3}}